decode_acc/__init__.py
decode_acc/accumulator.py
decode_acc/newlines.py
decode_acc/py.typed
decode_acc/util.py
decode_acc-1.1.1.dist-info/METADATA
decode_acc-1.1.1.dist-info/WHEEL
decode_acc-1.1.1.dist-info/top_level.txt
decode_acc-1.1.1.dist-info/zip-safe
decode_acc-1.1.1.dist-info/RECORD
