Metadata-Version: 2.1
Name: decode-acc
Version: 1.1.1
Summary: Incrementally decode bytes into strings and lines
Home-page: https://gitlab.com/ppentchev/decode-acc/
Author: Peter Pentchev
Author-email: roam@ringlet.net
License: BSD-2
Platform: UNKNOWN
Classifier: Development Status :: 5 - Production/Stable
Classifier: Intended Audience :: Developers
Classifier: License :: DFSG approved
Classifier: License :: Freely Distributable
Classifier: License :: OSI Approved :: BSD License
Classifier: Operating System :: OS Independent
Classifier: Programming Language :: Python
Classifier: Programming Language :: Python :: 3
Classifier: Programming Language :: Python :: 3.6
Classifier: Programming Language :: Python :: 3.7
Classifier: Programming Language :: Python :: 3.8
Classifier: Programming Language :: Python :: 3 :: Only
Classifier: Topic :: Software Development :: Libraries
Classifier: Topic :: Software Development :: Libraries :: Python Modules
Requires-Python: >= 3.6
Requires-Dist: dataclasses ; python_version < "3.7"
